nlallemantgetscode/__init__.py
nlallemantgetscode/script.py
nlallemantgetscode-0.1.0.dist-info/entry_points.txt
nlallemantgetscode-0.1.0.dist-info/WHEEL
nlallemantgetscode-0.1.0.dist-info/METADATA
nlallemantgetscode-0.1.0.dist-info/RECORD
