Metadata-Version: 2.1
Name: nlallemantgetscode
Version: 0.1.0
Summary: Print the HTTP status code for an HTTP GET
Home-page: https://gitlab.com/nlallemant/nlallemantgetscode
License: Apache-2.0
Keywords: requests,cli,status_code
Author: Nicolas LALLEMANT
Author-email: me@lall.fr
Requires-Python: >=3.6,<4.0
Classifier: License :: OSI Approved :: Apache Software License
Classifier: Programming Language :: Python :: 3
Classifier: Programming Language :: Python :: 3.6
Classifier: Programming Language :: Python :: 3.7
Classifier: Programming Language :: Python :: 3.8
Classifier: Programming Language :: Python :: 3.9
Requires-Dist: requests (>=2.25.0,<3.0.0)
